{
  "countries": [
    {
      "id": "sg",
      "name": "Singapore",
      "flag": "🇸🇬",
      "currency": "SGD (S$)",
      "workingHours": 44,
      "taxRules": "Progressive statutory tax rate from 0% up to 22%. CPF contribution required (up to 20% employee, up to 17% employer).",
      "overtimePolicy": "1.5x hourly rate for hours worked over 44 per week. Excludes executive/managerial roles.",
      "leavePolicy": "Minimum 14 days statutory paid annual leave + 14 days paid sick leave.",
      "holidayCalendar": "11 Gazetted Public Holidays (Chinese New Year, Hari Raya, National Day, Christmas, etc.)",
      "payrollCalendar": "Monthly payroll run on the 25th of each month.",
      "workflow": [
        "HR Draft",
        "Finance Review",
        "Country Admin Certification",
        "Executive Release"
      ],
      "readinessScore": 100,
      "complianceScore": 100,
      "dataQualityScore": 98,
      "status": "Completed",
      "riskLevel": "Low"
    },
    {
      "id": "de",
      "name": "Germany",
      "flag": "🇩🇪",
      "currency": "EUR (€)",
      "workingHours": 40,
      "taxRules": "Statutory income tax (Lohnsteuer) from 14% to 45%. Solidaritätszuschlag (5.5%). Health, pension, and unemployment social security (~20% employee, ~20% employer).",
      "overtimePolicy": "Max daily hours 8h. Extendable to 10h if average is 8h over 6 months. 11h consecutive rest required.",
      "leavePolicy": "Minimum 20 days paid annual leave based on 5-day week.",
      "holidayCalendar": "9-13 Public Holidays depending on federal state.",
      "payrollCalendar": "Monthly payroll run on the 28th of each month.",
      "workflow": [
        "HR Draft",
        "Compliance Verification",
        "Country Admin Certification",
        "Executive Release"
      ],
      "readinessScore": 92,
      "complianceScore": 94,
      "dataQualityScore": 91,
      "status": "Pending Approval",
      "riskLevel": "Medium"
    },
    {
      "id": "us",
      "name": "United States",
      "flag": "🇺🇸",
      "currency": "USD ($)",
      "workingHours": 40,
      "taxRules": "Federal income tax (10% to 37%), FICA (6.2% Social Security, 1.45% Medicare for both employee & employer), State and Local income taxes.",
      "overtimePolicy": "1.5x hourly rate for non-exempt employees working over 40 hours per week under FLSA rules.",
      "leavePolicy": "No statutory minimum paid leave. Left to employer/state policies.",
      "holidayCalendar": "11 Federal Holidays (New Year's, Memorial Day, July 4th, Thanksgiving, Christmas, etc.)",
      "payrollCalendar": "Semi-monthly on the 15th and last business day of the month.",
      "workflow": [
        "HR Draft",
        "Finance Review",
        "Audit Clearance",
        "Executive Release"
      ],
      "readinessScore": 74,
      "complianceScore": 82,
      "dataQualityScore": 86,
      "status": "Validating",
      "riskLevel": "High"
    },
    {
      "id": "jp",
      "name": "Japan",
      "flag": "🇯🇵",
      "currency": "JPY (¥)",
      "workingHours": 40,
      "taxRules": "National income tax (5% to 45%), Local inhabitant tax (10%), Social Insurance (Health, Pension, Long-term care, Employment).",
      "overtimePolicy": "Statutory premium is 1.25x for regular overtime, 1.35x for holiday work, 1.5x for late-night overtime (10pm-5am).",
      "leavePolicy": "10 days paid leave after 6 months of service, scaling to 20 days.",
      "holidayCalendar": "16 National Holidays (Golden Week, Mountain Day, Respect for the Aged Day, etc.)",
      "payrollCalendar": "Monthly payroll run on the 25th of each month.",
      "workflow": [
        "HR Draft",
        "Compliance Verification",
        "Executive Release"
      ],
      "readinessScore": 89,
      "complianceScore": 95,
      "dataQualityScore": 90,
      "status": "Pending Verification",
      "riskLevel": "Low"
    },
    {
      "id": "fr",
      "name": "France",
      "flag": "🇫🇷",
      "currency": "EUR (€)",
      "workingHours": 35,
      "taxRules": "Progressive personal tax, substantial employer social contributions (~45% of base wage), and employee contributions (~22%).",
      "overtimePolicy": "Hours 36-43 paid at 1.25x premium. Hours 44+ paid at 1.5x premium. RTT days offered for working hours over 35h.",
      "leavePolicy": "5 weeks (25 working days) paid annual leave + supplementary RTT days.",
      "holidayCalendar": "11 Public Holidays (Bastille Day, Armistice Day, Labour Day, etc.)",
      "payrollCalendar": "Monthly payroll run on the 30th of each month.",
      "workflow": [
        "HR Draft",
        "Finance Review",
        "Country Admin Certification",
        "Executive Release"
      ],
      "readinessScore": 65,
      "complianceScore": 78,
      "dataQualityScore": 81,
      "status": "Draft",
      "riskLevel": "Medium"
    },
    {
      "id": "in",
      "name": "India",
      "flag": "🇮🇳",
      "currency": "INR (₹)",
      "workingHours": 48,
      "taxRules": "Income tax slabs from 5% to 30% under New/Old Tax Regime. EPF contributions required (12% employee, 12% employer on basic pay). Professional Tax varies by state.",
      "overtimePolicy": "Double the ordinary hourly wage rate for any work performed beyond 9 hours in a day or 48 hours in a week under Factories Act.",
      "leavePolicy": "Minimum 15 days of earned leave (EL), 12 days of sick leave (SL) and casual leave (CL) as per Shops & Establishments Act.",
      "holidayCalendar": "3 Mandatory National Holidays (Republic Day, Independence Day, Gandhi Jayanti) + 10-15 Gazetted and Restricted Public Holidays based on state.",
      "payrollCalendar": "Monthly payroll run on the last working day of each month.",
      "workflow": [
        "HR Draft",
        "Finance Review",
        "Country Admin Certification",
        "Executive Release"
      ],
      "readinessScore": 100,
      "complianceScore": 100,
      "dataQualityScore": 100,
      "status": "Completed",
      "riskLevel": "Low"
    }
  ],
  "employees": [
    {
      "id": "EMP-1042",
      "name": "Anna Weber",
      "country": "Germany",
      "department": "Engineering",
      "title": "Principal Architect",
      "salary": 8500,
      "status": "Active"
    },
    {
      "id": "EMP-2109",
      "name": "Marcus Tan",
      "country": "Singapore",
      "department": "Product",
      "title": "Product Lead",
      "salary": 7800,
      "status": "Active"
    },
    {
      "id": "EMP-0098",
      "name": "Sarah Jenkins",
      "country": "United States",
      "department": "Sales",
      "title": "VP Global Sales",
      "salary": 12500,
      "status": "Active"
    },
    {
      "id": "EMP-3045",
      "name": "Hiroshi Sato",
      "country": "Japan",
      "department": "Operations",
      "title": "Director of Ops",
      "salary": 11000,
      "status": "Active"
    },
    {
      "id": "EMP-1204",
      "name": "Pierre Dubois",
      "country": "France",
      "department": "Marketing",
      "title": "Senior Manager",
      "salary": 6200,
      "status": "Active"
    },
    {
      "id": "EMP-8044",
      "name": "Amit Patel",
      "country": "India",
      "department": "Engineering",
      "title": "Lead Software Engineer",
      "salary": 120000,
      "status": "Active"
    }
  ],
  "validationResults": [
    {
      "id": "val-1",
      "employeeId": "EMP-1042",
      "employeeName": "Anna Weber",
      "country": "Germany",
      "issueType": "Overtime Violations",
      "severity": "High",
      "confidenceScore": 98,
      "explanation": "Worked 11.5 hours in a single shift, exceeding the 10-hour daily threshold mandated by the Germany Working Time Act (Arbeitszeitgesetz).",
      "recommendedResolution": "Convert excess 1.5 hours into TOIL (Time-Off-In-Lieu) balance and issue a formal compliance bypass log.",
      "status": "Pending"
    },
    {
      "id": "val-2",
      "employeeId": "EMP-2109",
      "employeeName": "Marcus Tan",
      "country": "Singapore",
      "issueType": "CPF Contribution Mismatch",
      "severity": "Medium",
      "confidenceScore": 95,
      "explanation": "HRMS records employee age as 54, triggering 20% employee CPF rate. Active payroll run calculated CPF at 15% based on stale Workday age bracket.",
      "recommendedResolution": "Apply retroactive adjustment S$ 250.00 to align payroll run with the true HRMS age status.",
      "status": "Pending"
    },
    {
      "id": "val-3",
      "employeeId": "EMP-0098",
      "employeeName": "Sarah Jenkins",
      "country": "United States",
      "issueType": "Base Salary Variance",
      "severity": "High",
      "confidenceScore": 92,
      "explanation": "Ingested base salary of $12,500.00 for the month is 25% higher than the HRMS active contract base salary of $10,000.00.",
      "recommendedResolution": "Reject the ingested timesheet rate and revert to the contract base salary, or request Compensation Team approval.",
      "status": "Pending"
    }
  ],
  "reconciliationResults": [
    {
      "id": "rec-1",
      "employeeId": "EMP-1042",
      "name": "Anna Weber",
      "source": "Timesheets (168h)",
      "target": "HRMS (160h)",
      "discrepancy": "+8.0 hrs Variance",
      "type": "Overtime Reconciliation",
      "confidence": 94,
      "aiRecommendation": "Authorize 8 hours overtime pay. Verified against automatic card badge-in security logs showing entry at 08:02 and exit at 18:35.",
      "status": "Pending"
    },
    {
      "id": "rec-2",
      "employeeId": "EMP-2109",
      "name": "Marcus Tan",
      "source": "Claims (S$ 420.00)",
      "target": "Policy Rule (S$ 300.00 Max)",
      "discrepancy": "S$ 120.00 Policy Overrun",
      "type": "Expense Inconsistency",
      "confidence": 89,
      "aiRecommendation": "Approve S$ 300.00 standard limit and route S$ 120.00 exception for Executive Sign-off due to offsite client dinner.",
      "status": "Pending"
    }
  ],
  "auditLogs": [
    {
      "id": "audit-1783591546504",
      "timestamp": "2026-07-09T10:05:46.504Z",
      "user": "Ronak Surve",
      "role": "Super Admin",
      "action": "MFA OTP Sent (SSO)",
      "details": "Simulated Email OTP [309998] sent to ronaksurve96@gmail.com (expires in 5m)."
    },
    {
      "id": "audit-1783591455612",
      "timestamp": "2026-07-09T10:04:15.612Z",
      "user": "Ronak Surve",
      "role": "Super Admin",
      "action": "MFA OTP Sent (SSO)",
      "details": "Simulated Email OTP [715226] sent to ronaksurve96@gmail.com (expires in 5m)."
    },
    {
      "id": "audit-1783589299670",
      "timestamp": "2026-07-09T09:28:19.670Z",
      "user": "Ronak Surve",
      "role": "Super Admin",
      "action": "MFA OTP Sent (SSO)",
      "details": "Simulated Email OTP [487163] sent to ronaksurve96@gmail.com (expires in 5m)."
    },
    {
      "id": "audit-1783588500315",
      "timestamp": "2026-07-09T09:15:00.315Z",
      "user": "Ronak Surve",
      "role": "Super Admin",
      "action": "MFA OTP Sent (SSO)",
      "details": "Simulated Email OTP [352916] sent to ronaksurve96@gmail.com (expires in 5m)."
    },
    {
      "id": "audit-1783588342404",
      "timestamp": "2026-07-09T09:12:22.404Z",
      "user": "Ronak Surve",
      "role": "Super Admin",
      "action": "MFA OTP Sent (SSO)",
      "details": "Simulated Email OTP [277900] sent to ronaksurve96@gmail.com (expires in 5m)."
    },
    {
      "id": "audit-1783586599513",
      "timestamp": "2026-07-09T08:43:19.513Z",
      "user": "Ronak Surve",
      "role": "Super Admin",
      "action": "MFA OTP Sent (SSO)",
      "details": "Simulated Email OTP [622213] sent to ronaksurve96@gmail.com (expires in 5m)."
    },
    {
      "id": "audit-1783586177436",
      "timestamp": "2026-07-09T08:36:17.436Z",
      "user": "Ronak Surve",
      "role": "Super Admin",
      "action": "MFA OTP Sent (SSO)",
      "details": "Simulated Email OTP [151863] sent to ronaksurve@gmail.com (expires in 5m)."
    },
    {
      "id": "audit-1",
      "timestamp": "2026-07-09T08:35:38.893Z",
      "user": "System",
      "role": "Super Admin",
      "action": "Database Initialized",
      "details": "Seeded initial dynamic compliance rosters, countries, and audit results."
    }
  ],
  "users": [
    {
      "id": "user-1",
      "name": "Ronak Surve",
      "psNumber": "PS-09600",
      "email": "ronaksurve96@gmail.com",
      "department": "Executive Office",
      "country": "India",
      "roles": [
        "Super Admin",
        "Executive Leadership"
      ],
      "status": "Active",
      "password": "Password123!",
      "lastLogin": "2026-07-09T10:07:25.458Z",
      "failedLoginAttempts": 0,
      "mfaEnabled": true,
      "passwordExpiryDate": "2026-10-01",
      "mfaStatus": "Enabled"
    },
    {
      "id": "user-2",
      "name": "John Smith",
      "psNumber": "PS-00122",
      "email": "john.smith@nexus-corp.com",
      "department": "HR",
      "country": "Singapore",
      "roles": [
        "HR",
        "Payroll Administrator",
        "Country Payroll Administrator"
      ],
      "status": "Active",
      "password": "Password123!",
      "lastLogin": "2026-07-05T09:12:00Z",
      "failedLoginAttempts": 0,
      "mfaEnabled": true,
      "passwordExpiryDate": "2026-09-15",
      "mfaStatus": "Enabled"
    },
    {
      "id": "user-3",
      "name": "Emma Watson",
      "psNumber": "PS-02241",
      "email": "emma.watson@nexus-corp.com",
      "department": "Finance",
      "country": "Germany",
      "roles": [
        "Finance",
        "Compliance Officer"
      ],
      "status": "Active",
      "password": "Password123!",
      "lastLogin": "2026-07-04T14:22:00Z",
      "failedLoginAttempts": 0,
      "mfaEnabled": false,
      "passwordExpiryDate": "2026-08-01",
      "mfaStatus": "Disabled"
    },
    {
      "id": "user-4",
      "name": "Kenji Sato",
      "psNumber": "PS-03310",
      "email": "kenji.sato@nexus-corp.com",
      "department": "Operations",
      "country": "Japan",
      "roles": [
        "Country Payroll Administrator",
        "Auditor"
      ],
      "status": "Locked",
      "password": "Password123!",
      "lastLogin": "2026-07-01T11:05:00Z",
      "failedLoginAttempts": 5,
      "mfaEnabled": true,
      "passwordExpiryDate": "2026-07-30",
      "mfaStatus": "Enabled"
    },
    {
      "id": "user-charmi",
      "name": "Charmi Patel",
      "psNumber": "PS-08045",
      "email": "charmipatel@gmail.com",
      "department": "HR",
      "country": "India",
      "roles": [
        "HR"
      ],
      "status": "Active",
      "password": "123456",
      "lastLogin": "2026-07-09T10:00:00Z",
      "failedLoginAttempts": 0,
      "mfaEnabled": false,
      "passwordExpiryDate": "2027-12-31",
      "mfaStatus": "Disabled"
    },
    {
      "id": "user-super-admin",
      "name": "Ronak Surve",
      "psNumber": "PS-09999",
      "email": "ronaksurve@gmail.com",
      "department": "Executive Office",
      "country": "India",
      "roles": [
        "Super Admin",
        "Executive Leadership"
      ],
      "status": "Active",
      "password": "Fy2crhwww@",
      "lastLogin": "2026-07-09T08:36:27.143Z",
      "failedLoginAttempts": 0,
      "mfaEnabled": true,
      "passwordExpiryDate": "2027-12-31",
      "mfaStatus": "Enabled"
    }
  ],
  "permissions": [
    {
      "id": "perm-1",
      "role": "Super Admin",
      "permissions": {
        "Payroll Upload": true,
        "Validation": true,
        "Approvals": true,
        "Reports": true,
        "Audit": true,
        "Country Rules": true,
        "Administration": true,
        "User Management": true
      }
    },
    {
      "id": "perm-2",
      "role": "Payroll Administrator",
      "permissions": {
        "Payroll Upload": true,
        "Validation": true,
        "Approvals": false,
        "Reports": true,
        "Audit": true,
        "Country Rules": false,
        "Administration": false,
        "User Management": false
      }
    },
    {
      "id": "perm-3",
      "role": "Country Payroll Administrator",
      "permissions": {
        "Payroll Upload": true,
        "Validation": true,
        "Approvals": true,
        "Reports": true,
        "Audit": true,
        "Country Rules": true,
        "Administration": false,
        "User Management": false
      }
    },
    {
      "id": "perm-4",
      "role": "HR",
      "permissions": {
        "Payroll Upload": true,
        "Validation": true,
        "Approvals": false,
        "Reports": true,
        "Audit": false,
        "Country Rules": false,
        "Administration": false,
        "User Management": false
      }
    },
    {
      "id": "perm-5",
      "role": "Finance",
      "permissions": {
        "Payroll Upload": false,
        "Validation": false,
        "Approvals": true,
        "Reports": true,
        "Audit": true,
        "Country Rules": false,
        "Administration": false,
        "User Management": false
      }
    },
    {
      "id": "perm-6",
      "role": "Compliance Officer",
      "permissions": {
        "Payroll Upload": false,
        "Validation": true,
        "Approvals": false,
        "Reports": true,
        "Audit": true,
        "Country Rules": true,
        "Administration": false,
        "User Management": false
      }
    },
    {
      "id": "perm-7",
      "role": "Auditor",
      "permissions": {
        "Payroll Upload": false,
        "Validation": false,
        "Approvals": false,
        "Reports": true,
        "Audit": true,
        "Country Rules": false,
        "Administration": false,
        "User Management": false
      }
    },
    {
      "id": "perm-8",
      "role": "Executive Leadership",
      "permissions": {
        "Payroll Upload": false,
        "Validation": false,
        "Approvals": false,
        "Reports": true,
        "Audit": true,
        "Country Rules": false,
        "Administration": false,
        "User Management": false
      }
    }
  ],
  "loginLogs": [
    {
      "id": "log-1783591645459",
      "timestamp": "2026-07-09T10:07:25.459Z",
      "email": "ronaksurve96@gmail.com",
      "name": "Ronak Surve",
      "browser": "Chrome",
      "device": "Windows Desktop",
      "ip": "192.168.1.111",
      "method": "MFA OTP Verification",
      "status": "Success"
    },
    {
      "id": "log-1783591465455",
      "timestamp": "2026-07-09T10:04:25.455Z",
      "email": "ronaksurve96@gmail.com",
      "name": "Ronak Surve",
      "browser": "Chrome",
      "device": "Windows Desktop",
      "ip": "192.168.1.111",
      "method": "MFA OTP Verification",
      "status": "Success"
    },
    {
      "id": "log-1783589305770",
      "timestamp": "2026-07-09T09:28:25.770Z",
      "email": "ronaksurve96@gmail.com",
      "name": "Ronak Surve",
      "browser": "Chrome",
      "device": "Windows Desktop",
      "ip": "192.168.1.111",
      "method": "MFA OTP Verification",
      "status": "Success"
    },
    {
      "id": "log-1783588510436",
      "timestamp": "2026-07-09T09:15:10.436Z",
      "email": "ronaksurve96@gmail.com",
      "name": "Ronak Surve",
      "browser": "Chrome",
      "device": "Windows Desktop",
      "ip": "192.168.1.111",
      "method": "MFA OTP Verification",
      "status": "Success"
    },
    {
      "id": "log-1783588349562",
      "timestamp": "2026-07-09T09:12:29.562Z",
      "email": "ronaksurve96@gmail.com",
      "name": "Ronak Surve",
      "browser": "Chrome",
      "device": "Windows Desktop",
      "ip": "192.168.1.111",
      "method": "MFA OTP Verification",
      "status": "Success"
    },
    {
      "id": "log-1783586607123",
      "timestamp": "2026-07-09T08:43:27.123Z",
      "email": "ronaksurve96@gmail.com",
      "name": "Ronak Surve",
      "browser": "Chrome",
      "device": "Windows Desktop",
      "ip": "192.168.1.111",
      "method": "MFA OTP Verification",
      "status": "Success"
    },
    {
      "id": "log-1783586187144",
      "timestamp": "2026-07-09T08:36:27.144Z",
      "email": "ronaksurve@gmail.com",
      "name": "Ronak Surve",
      "browser": "Chrome",
      "device": "Windows Desktop",
      "ip": "192.168.1.111",
      "method": "MFA OTP Verification",
      "status": "Success"
    },
    {
      "id": "log-1",
      "timestamp": "2026-07-06T10:25:00Z",
      "email": "ronaksurve96@gmail.com",
      "name": "Ronak Surve",
      "browser": "Chrome",
      "device": "Windows Desktop",
      "ip": "192.168.1.55",
      "method": "Microsoft SSO",
      "status": "Success"
    },
    {
      "id": "log-2",
      "timestamp": "2026-07-06T10:15:00Z",
      "email": "kenji.sato@nexus-corp.com",
      "name": "Kenji Sato",
      "browser": "Safari",
      "device": "macOS Laptop",
      "ip": "203.112.45.18",
      "method": "Password",
      "status": "Failed",
      "details": "Incorrect password attempt 5 - account locked."
    },
    {
      "id": "log-3",
      "timestamp": "2026-07-05T09:12:00Z",
      "email": "john.smith@nexus-corp.com",
      "name": "John Smith",
      "browser": "Edge",
      "device": "Windows Desktop",
      "ip": "10.0.4.120",
      "method": "Microsoft SSO",
      "status": "Success"
    }
  ]
}